ujeebu_scrapy/__init__.py
ujeebu_scrapy/ujeebu_middleware.py
ujeebu_scrapy/ujeebu_request.py
ujeebu_scrapy-0.2.2.dist-info/licenses/LICENSE
ujeebu_scrapy-0.2.2.dist-info/METADATA
ujeebu_scrapy-0.2.2.dist-info/WHEEL
ujeebu_scrapy-0.2.2.dist-info/top_level.txt
ujeebu_scrapy-0.2.2.dist-info/RECORD
