Metadata-Version: 2.4
Name: ujeebu_scrapy
Version: 0.2.2
Summary: Scrapy middleware to use Ujeebu scrape API
Home-page: https://github.com/ujeebu/ujeebu_scrapy
Author: Ujeebu
Author-email: y.alhyane@gmail.com
License: MIT license
Keywords: ujeebu_scrapy
Classifier: Development Status :: 2 - Pre-Alpha
Classifier: Intended Audience :: Developers
Classifier: License :: OSI Approved :: MIT License
Classifier: Natural Language :: English
Classifier: Programming Language :: Python :: 3
Classifier: Programming Language :: Python :: 3.6
Classifier: Programming Language :: Python :: 3.7
Classifier: Programming Language :: Python :: 3.8
Requires-Python: >=3.6
License-File: LICENSE
Requires-Dist: scrapy
Dynamic: author
Dynamic: author-email
Dynamic: classifier
Dynamic: description
Dynamic: description-content-type
Dynamic: home-page
Dynamic: keywords
Dynamic: license
Dynamic: license-file
Dynamic: requires-dist
Dynamic: requires-python
Dynamic: summary
